drf_extra_fields/__init__.py
drf_extra_fields/compat.py
drf_extra_fields/fields.py
drf_extra_fields/geo_fields.py
drf_extra_fields/relations.py
drf_extra_fields/runtests/__init__.py
drf_extra_fields/runtests/settings.py
django_extra_fields-3.0.0.dist-info/LICENSE
django_extra_fields-3.0.0.dist-info/METADATA
django_extra_fields-3.0.0.dist-info/WHEEL
django_extra_fields-3.0.0.dist-info/top_level.txt
django_extra_fields-3.0.0.dist-info/RECORD
